deepesn/__init__.py
deepesn/configurations.py
deepesn/deepesn.py
deepesn/metrics.py
deepesn/task.py
deepesn-1.1.5.dist-info/LICENSE
deepesn-1.1.5.dist-info/METADATA
deepesn-1.1.5.dist-info/WHEEL
deepesn-1.1.5.dist-info/top_level.txt
deepesn-1.1.5.dist-info/RECORD
